{
    "type": "minecraft:chest",
    "pools": [
        {
            "rolls": 1,
            "bonus_rolls": 0,
            "entries": [
                {
                    "type": "minecraft:item",
                    "name": "minecraft:gunpowder",
                    "weight": 100,
                    "functions": [
                        {
                            "function": "limit_count",
                            "limit": 8
                        }
                    ]
                },
                {
                    "type": "minecraft:item",
                    "name": "minecraft:string",
                    "weight": 50,
                    "functions": [
                        {
                            "function": "limit_count",
                            "limit": 8
                        }
                    ]
                },
                {
                    "type": "minecraft:item",
                    "name": "minecraft:bone",
                    "weight": 20,
                    "functions": [
                        {
                            "function": "limit_count",
                            "limit": 8
                        }
                    ]
                },
                {
                    "type": "minecraft:item",
                    "name": "minecraft:spider_eye",
                    "weight": 10,
                    "functions": [
                        {
                            "function": "limit_count",
                            "limit": 8
                        }
                    ]
                },
                {
                    "type": "minecraft:item",
                    "name": "minecraft:ender_pearl",
                    "weight": 5,
                    "functions": [
                        {
                            "function": "limit_count",
                            "limit": 2
                        }
                    ]
                },
                {
                    "type": "minecraft:item",
                    "name": "minecraft:music_disc_13",
                    "weight": 1,
                    "functions": [
                        {
                            "function": "limit_count",
                            "limit": 1
                        }
                    ]
                }
            ]
        }
    ]
}
